{"_id":"57cc7664a43bf14533b0d675","teamName":"Weird","country":"United States","openGold":"Russia (RUS)","openSilver":"United States of America (USA)","openBronze":"Cuba (CUB)","openIndGold":"CHI\tVasquez Schroeder Rodrigo \t2546\t–\t3400042","womenGold":"China (CHN)","womenSilver":"Russia (RUS)","womenBronze":"Cuba (CUB)","womenIndGold":"ARG\tLujan Carolina \t2378\t–\t109878","__v":0,"iso":"US","score":[{"r1":27,"r2":23,"r3":14,"r4":18,"r5":19,"r6":0,"r7":0,"r8":0,"r9":0,"r10":0,"r11":0,"total":101}],"players":[{"_id":"57caa1cd4048d8b01e743ecd","id":2020009,"rank":3,"name":"Caruana Fabiano","rating":2808,"title":"GM","country":"United States of America","team":"United States of America","fed":"USA","board":1,"eventType":"open","__v":0,"roundResults":[{"round":2,"result":"1","points":4,"colour":"b"},{"round":3,"result":"1","points":3,"colour":"w"},{"round":4,"result":"½","points":2,"colour":"w"},{"round":5,"result":"½","points":2,"colour":"b"}]},{"_id":"57caa1cd4048d8b01e743f05","id":4675789,"rank":58,"name":"Meier Georg","rating":2654,"title":"GM","country":"Germany","team":"Germany","fed":"GER","board":2,"eventType":"open","__v":0,"roundResults":[{"round":1,"result":"½","points":2,"colour":"b"},{"round":2,"result":"½","points":2,"colour":"w"},{"round":4,"result":"½","points":2,"colour":"b"},{"round":5,"result":"1","points":3,"colour":"w"}]},{"_id":"57caa1cd4048d8b01e743f6b","id":3409350,"rank":217,"name":"Henriquez Villagra Cristobal","rating":2508,"title":"IM","country":"Chile","team":"Chile","fed":"CHI","board":3,"eventType":"open","__v":0,"roundResults":[{"round":1,"result":"1","points":4,"colour":"b"},{"round":2,"result":"½","points":2,"colour":"w"},{"round":4,"result":"1","points":4,"colour":"b"},{"round":5,"result":"1","points":4,"colour":"b"}]},{"_id":"57caa1cd4048d8b01e743eec","id":13402129,"rank":34,"name":"Safarli Eltaj","rating":2688,"title":"GM","country":"Azerbaijan 1","team":"Azerbaijan 1","fed":"AZE","board":5,"eventType":"open","__v":0,"roundResults":[{"round":1,"result":"1","points":4,"colour":"b"},{"round":5,"result":"½","points":2,"colour":"b"}]},{"_id":"57caa1cd4048d8b01e744205","id":3503321,"rank":169,"name":"Gonzalez Vidal Yuri","rating":2553,"title":"GM","country":"Cuba","team":"Cuba","fed":"CUB","board":5,"eventType":"open","__v":0,"roundResults":[{"round":1,"result":"½","points":2,"colour":"w"},{"round":2,"result":"1","points":3,"colour":"w"},{"round":5,"result":"0","points":1,"colour":"b"}]},{"_id":"57caa1d34048d8b01e744294","id":4404564,"rank":81,"name":"Rodriguez Rueda Paula Andrea","rating":2326,"title":"IM","country":"Colombia","team":"Colombia","fed":"COL","board":1,"eventType":"women","__v":0,"roundResults":[{"round":1,"result":"1","points":3,"colour":"w"},{"round":2,"result":"½","points":2,"colour":"b"},{"round":3,"result":"½","points":2,"colour":"b"},{"round":4,"result":"½","points":2,"colour":"w"},{"round":5,"result":"½","points":2,"colour":"w"}]},{"_id":"57caa1d34048d8b01e74425c","id":2012782,"rank":25,"name":"Krush Irina","rating":2444,"title":"GM","country":"United States of America","team":"United States of America","fed":"USA","board":1,"eventType":"women","__v":0,"roundResults":[{"round":1,"result":"1","points":4,"colour":"b"},{"round":2,"result":"½","points":2,"colour":"w"},{"round":3,"result":"½","points":2,"colour":"w"},{"round":4,"result":"½","points":2,"colour":"b"},{"round":5,"result":"0","points":1,"colour":"w"}]},{"_id":"57caa1d34048d8b01e7442bb","id":3504794,"rank":114,"name":"Linares Napoles Oleiny","rating":2276,"title":"WGM","country":"Cuba","team":"Cuba","fed":"CUB","board":3,"eventType":"women","__v":0,"roundResults":[{"round":1,"result":"1","points":4,"colour":"b"},{"round":2,"result":"1","points":4,"colour":"b"},{"round":3,"result":"½","points":2,"colour":"w"},{"round":4,"result":"½","points":2,"colour":"b"},{"round":5,"result":"0","points":1,"colour":"w"}]},{"_id":"57caa1d34048d8b01e744257","id":4147103,"rank":14,"name":"Goryachkina Aleksandra","rating":2475,"title":"WGM","country":"Russia","team":"Russia","fed":"RUS","board":3,"eventType":"women","__v":0,"roundResults":[{"round":1,"result":"1","points":4,"colour":"b"},{"round":2,"result":"1","points":3,"colour":"w"},{"round":3,"result":"½","points":2,"colour":"w"},{"round":4,"result":"½","points":2,"colour":"b"}]},{"_id":"57caa1d34048d8b01e744369","id":3503844,"rank":291,"name":"Bosch Garcia Jacqueline","rating":2011,"title":"WFM","country":"Ecuador","team":"Ecuador","fed":"ECU","board":5,"eventType":"women","__v":0,"roundResults":[{"round":2,"result":"0","points":1,"colour":"b"},{"round":3,"result":"1","points":3,"colour":"w"},{"round":4,"result":"½","points":2,"colour":"b"},{"round":5,"result":"1","points":3,"colour":"w"}]}],"playerIds":[]}