{"_id":"57cc7664a43bf14533b0d63b","teamName":"SimpleZugzwang","score":[{"r1":27,"r2":14,"r3":18,"r4":0,"r5":0,"r6":0,"r7":0,"r8":0,"r9":0,"r10":0,"r11":0,"total":59}],"players":[{"_id":"57caa1cd4048d8b01e743eed","id":1202758,"rank":35,"name":"Nisipeanu Liviu-Dieter","rating":2687,"title":"GM","country":"Germany","team":"Germany","fed":"GER","board":1,"eventType":"open","__v":0,"roundResults":[{"round":2,"result":"½","points":2,"colour":"b"},{"round":3,"result":"½","points":2,"colour":"w"}]},{"_id":"57caa1cd4048d8b01e743ecf","id":2016192,"rank":5,"name":"Nakamura Hikaru","rating":2789,"title":"GM","country":"United States of America","team":"United States of America","fed":"USA","board":2,"eventType":"open","__v":0,"roundResults":[{"round":1,"result":"1","points":3,"colour":"w"},{"round":2,"result":"1","points":3,"colour":"w"},{"round":3,"result":"½","points":2,"colour":"b"}]},{"_id":"57caa1cd4048d8b01e743f2e","id":2804344,"rank":97,"name":"Postny Evgeny","rating":2619,"title":"GM","country":"Israel","team":"Israel","fed":"ISR","board":2,"eventType":"open","__v":0,"roundResults":[{"round":1,"result":"1","points":3,"colour":"w"},{"round":3,"result":"½","points":2,"colour":"b"}]},{"_id":"57caa1cd4048d8b01e743f13","id":5021596,"rank":74,"name":"Sethuraman S.P.","rating":2640,"title":"GM","country":"India","team":"India","fed":"IND","board":4,"eventType":"open","__v":0,"roundResults":[{"round":1,"result":"1","points":4,"colour":"b"},{"round":2,"result":"1","points":3,"colour":"w"},{"round":3,"result":"½","points":2,"colour":"w"}]},{"_id":"57caa1cd4048d8b01e743ee0","id":4147235,"rank":22,"name":"Tomashevsky Evgeny","rating":2731,"title":"GM","country":"Russia","team":"Russia","fed":"RUS","board":3,"eventType":"open","__v":0,"roundResults":[{"round":1,"result":"1","points":3,"colour":"w"},{"round":3,"result":"½","points":2,"colour":"w"}]},{"_id":"57caa1d34048d8b01e74424c","id":4128125,"rank":6,"name":"Kosteniuk Alexandra","rating":2538,"title":"GM","country":"Russia","team":"Russia","fed":"RUS","board":1,"eventType":"women","__v":0,"roundResults":[{"round":1,"result":"1","points":3,"colour":"w"},{"round":3,"result":"1","points":3,"colour":"w"}]},{"_id":"57caa1d34048d8b01e74424b","id":14114550,"rank":5,"name":"Muzychuk Mariya","rating":2539,"title":"GM","country":"Ukraine","team":"Ukraine","fed":"UKR","board":2,"eventType":"women","__v":0,"roundResults":[{"round":1,"result":"1","points":4,"colour":"b"},{"round":3,"result":"½","points":2,"colour":"w"}]},{"_id":"57caa1d34048d8b01e74429a","id":4690745,"rank":84,"name":"Lubbe Melanie","rating":2324,"title":"WGM","country":"Germany","team":"Germany","fed":"GER","board":4,"eventType":"women","__v":0,"roundResults":[{"round":1,"result":"1","points":4,"colour":"b"},{"round":2,"result":"1","points":3,"colour":"w"},{"round":3,"result":"0","points":1,"colour":"b"}]},{"_id":"57caa1d34048d8b01e7442d9","id":1033689,"rank":148,"name":"Kazarian Anna-Maja","rating":2231,"title":"FM","country":"Netherlands","team":"Netherlands","fed":"NED","board":4,"eventType":"women","__v":0,"roundResults":[{"round":1,"result":"1","points":3,"colour":"w"},{"round":2,"result":"1","points":3,"colour":"w"},{"round":3,"result":"½","points":2,"colour":"b"}]},{"_id":"57caa1d34048d8b01e7442b5","id":1212915,"rank":112,"name":"Foisor Sabina-Francesca","rating":2279,"title":"WGM","country":"United States of America","team":"United States of America","fed":"USA","board":5,"eventType":"women","__v":0,"roundResults":[]}]}